{
  "xMax": 500,
  "yMax": 375,
  "image": "assets/podklad-nakres.jpg",
  "zones": [
    { "name": "Pod záhradou", "color": "#22c55e", "points": "22,40 198,40 198,70 22,70" },
    { "name": "Medza", "color": "#84cc16", "points": "205,42 470,42 470,78 205,78" },
    { "name": "Predok", "color": "#10b981", "points": "22,80 145,80 145,250 22,250" },
    { "name": "Záhrada", "color": "#22c55e", "points": "150,82 205,82 205,172 150,172" },
    { "name": "Čerešňa", "color": "#14b8a6", "points": "210,90 258,90 258,198 210,198" },
    { "name": "Rola", "color": "#84cc16", "points": "265,80 470,80 470,135 265,135" },
    { "name": "Nad rolou", "color": "#22c55e", "points": "268,140 378,140 378,180 268,180" },
    { "name": "Poličko", "color": "#f59e0b", "points": "384,135 426,135 426,180 384,180" },
    { "name": "Hnojisko", "color": "#78716c", "points": "430,135 472,135 472,180 430,180" },
    { "name": "Dom", "color": "#78716c", "points": "150,182 198,182 198,228 150,228" },
    { "name": "Dre", "color": "#78716c", "points": "228,180 262,180 262,207 228,207" },
    { "name": "Kurník", "color": "#78716c", "points": "266,184 302,184 302,212 266,212" },
    { "name": "K poličku", "color": "#22c55e", "points": "308,184 378,184 378,216 308,216" },
    { "name": "Drevareň", "color": "#78716c", "points": "210,208 265,208 265,240 210,240" },
    { "name": "Altánok", "color": "#f59e0b", "points": "288,220 356,220 356,292 288,292" },
    { "name": "Zadok", "color": "#10b981", "points": "384,225 462,225 462,325 384,325" },
    { "name": "Garáž", "color": "#78716c", "points": "214,255 282,255 282,292 214,292" },
    { "name": "Dvor", "color": "#84cc16", "points": "55,235 205,235 205,295 55,295" },
    { "name": "Garaz", "color": "#78716c", "points": "22,296 300,296 300,326 22,326" },
    { "name": "Jablon", "color": "#22c55e", "points": "300,292 384,292 384,330 300,330" },
    { "name": "WC", "color": "#78716c", "points": "452,254 492,254 492,282 452,282" },
    { "name": "SI", "color": "#78716c", "points": "452,285 492,285 492,306 452,306" },
    { "name": "V", "color": "#0ea5e9", "points": "452,310 492,310 492,336 452,336" }
  ]
}
